epiwrap/__init__.py
epiwrap/intra.py
epiwrap-0.1.3.dist-info/LICENSE
epiwrap-0.1.3.dist-info/METADATA
epiwrap-0.1.3.dist-info/WHEEL
epiwrap-0.1.3.dist-info/top_level.txt
epiwrap-0.1.3.dist-info/RECORD
