Metadata-Version: 2.1
Name: epiwrap
Version: 0.1.3
Summary: A local wrapper for the epitech intranet
Home-page: https://github.com/Waz0x/EpiWrap
Author: Waz0x
Author-email: remy.noulin@epitech.eu
License: UNKNOWN
Project-URL: Bug Tracker, https://github.com/Waz0x/EpiWrap/issues
Platform: UNKNOWN
Classifier: Programming Language :: Python :: 3
Classifier: License :: OSI Approved :: MIT License
Classifier: Operating System :: OS Independent
Requires-Python: >=3.8
License-File: LICENSE
